systemize/__init__.py
systemize-0.0.1.dist-info/LICENCE.txt
systemize-0.0.1.dist-info/METADATA
systemize-0.0.1.dist-info/WHEEL
systemize-0.0.1.dist-info/top_level.txt
systemize-0.0.1.dist-info/RECORD
