Metadata-Version: 2.1
Name: systemize
Version: 0.0.1
Summary: Systemize automatically organizes all of your files into the grouping of a similar kind together, getting rid of clutter
Home-page: https://github.com/ayushman17/Systemize
Author: Ayushman Singh Chauhan
Author-email: ascb508@gmail.com
License: UNKNOWN
Platform: UNKNOWN
Classifier: Programming Language :: Python :: 3
Classifier: License :: OSI Approved :: MIT License
Classifier: Operating System :: OS Independent
